{
	"info": {
		"_postman_id": "4168939a-984b-495e-879a-b7dbf20e5f3a",
		"name": "auth",
		"schema": "https://schema.getpostman.com/json/collection/v2.1.0/collection.json",
		"_exporter_id": "14487413"
	},
	"item": [
		{
			"name": "login",
			"request": {
				"method": "POST",
				"header": [],
				"url": {
					"raw": "http://localhost:8000/auth/login",
					"protocol": "http",
					"host": [
						"localhost"
					],
					"port": "8000",
					"path": [
						"auth",
						"login"
					]
				}
			},
			"response": []
		}
	]
}